src/Certifik8/__init__.py
src/Certifik8/certificado.py
src/Certifik8/data_emissao.py
src/Certifik8/html2pdf.py
src/Certifik8/main.py
certifikadas8-0.1.1.dist-info/WHEEL
certifikadas8-0.1.1.dist-info/LICENSE
certifikadas8-0.1.1.dist-info/METADATA
certifikadas8-0.1.1.dist-info/entry_points.txt
certifikadas8-0.1.1.dist-info/RECORD
