Metadata-Version: 2.1
Name: certifikadas8
Version: 0.1.1
Summary: Certifik8 é um gerador de certificados automático criado em Python. O projeto busca facilitar a geração massiva de documentos a serem emitidos após algum evento.
Home-page: https://github.com/fga-eps-mds/Certifik8
License: MIT
Author: Victorio
Author-email: victorio.lazaro15@gmail.com
Requires-Python: >=3.10,<4.0
Classifier: License :: OSI Approved :: MIT License
Classifier: Programming Language :: Python :: 3
Classifier: Programming Language :: Python :: 3.10
Classifier: Programming Language :: Python :: 3.11
Requires-Dist: Pillow (==9.3.0)
Requires-Dist: PyPDF2 (==2.11.1)
Requires-Dist: beautifulsoup4 (>=4.11.1,<5.0.0)
Requires-Dist: openpyxl (>=3.0.10,<4.0.0)
Requires-Dist: pandas (==1.5.2)
Requires-Dist: pdfkit (==1.0.0)
Requires-Dist: pendulum (>=2.1.2,<3.0.0)
Requires-Dist: setuptools (==65.6.3)
Project-URL: Repository, https://github.com/fga-eps-mds/Certifik8
